dimples/__init__.py
dimples/emitter.py
dimples/client/__init__.py
dimples/client/checker.py
dimples/client/checkpoint.py
dimples/client/facebook.py
dimples/client/messenger.py
dimples/client/packer.py
dimples/client/processor.py
dimples/client/terminal.py
dimples/client/cpu/__init__.py
dimples/client/cpu/commands.py
dimples/client/cpu/creator.py
dimples/client/cpu/customized.py
dimples/client/cpu/group.py
dimples/client/cpu/grp_expel.py
dimples/client/cpu/grp_invite.py
dimples/client/cpu/grp_join.py
dimples/client/cpu/grp_query.py
dimples/client/cpu/grp_quit.py
dimples/client/cpu/grp_reset.py
dimples/client/cpu/grp_resign.py
dimples/client/cpu/handshake.py
dimples/client/network/__init__.py
dimples/client/network/session.py
dimples/client/network/state.py
dimples/client/network/transition.py
dimples/common/__init__.py
dimples/common/anonymous.py
dimples/common/ans.py
dimples/common/archivist.py
dimples/common/checker.py
dimples/common/facebook.py
dimples/common/messenger.py
dimples/common/packer.py
dimples/common/processer.py
dimples/common/queue.py
dimples/common/register.py
dimples/common/session.py
dimples/common/compat/__init__.py
dimples/common/compat/address.py
dimples/common/compat/compatible.py
dimples/common/compat/compressor.py
dimples/common/compat/entity.py
dimples/common/compat/loader.py
dimples/common/compat/meta.py
dimples/common/compat/network.py
dimples/common/dbi/__init__.py
dimples/common/dbi/account.py
dimples/common/dbi/message.py
dimples/common/dbi/session.py
dimples/common/protocol/__init__.py
dimples/common/protocol/ans.py
dimples/common/protocol/block.py
dimples/common/protocol/groups.py
dimples/common/protocol/handshake.py
dimples/common/protocol/login.py
dimples/common/protocol/mute.py
dimples/common/protocol/password.py
dimples/common/protocol/report.py
dimples/common/protocol/roles.py
dimples/common/protocol/utils.py
dimples/common/protocol/version.py
dimples/conn/__init__.py
dimples/conn/flexible.py
dimples/conn/gate.py
dimples-1.5.9.dist-info/LICENSE
dimples-1.5.9.dist-info/METADATA
dimples-1.5.9.dist-info/WHEEL
dimples-1.5.9.dist-info/entry_points.txt
dimples-1.5.9.dist-info/top_level.txt
dimples-1.5.9.dist-info/RECORD
