Metadata-Version: 2.1
Name: dimples
Version: 1.5.9
Summary: DIMP Library for Edges and Stations
Home-page: https://github.com/dimchat/demo-py
Author: Albert Moky
Author-email: albert.moky@gmail.com
License: MIT
Classifier: Programming Language :: Python :: 3
Classifier: License :: OSI Approved :: MIT License
Classifier: Operating System :: OS Independent
License-File: LICENSE
Requires-Dist: requests
Requires-Dist: dimplugins (>=2.3.4)
Requires-Dist: dimsdk (>=2.3.4)
Requires-Dist: startrek (>=2.2.2)
Requires-Dist: tcp (>=2.2.2)
Requires-Dist: udp (>=2.2.2)
Requires-Dist: aiou (>=1.1.0)
